noelnetwork/__init__.py
noelnetwork/neural.py
noelnetwork-1.0.3.dist-info/METADATA
noelnetwork-1.0.3.dist-info/WHEEL
noelnetwork-1.0.3.dist-info/top_level.txt
noelnetwork-1.0.3.dist-info/RECORD
