Metadata-Version: 2.1
Name: noelnetwork
Version: 1.0.3
Summary: Create and use Neural Networks
Home-page: https://github.com/noel-friedrich/neural
Author: Noel Friedrich
Author-email: noel.friedrich@outlook.de
License: MIT
Platform: UNKNOWN
Classifier: License :: OSI Approved :: MIT License
Classifier: Programming Language :: Python :: 3
Classifier: Programming Language :: Python :: 3.7
